work_ninja.pypy39-pp73-x86-linux-gnu.so
workninja-0.0.1.dist-info/WHEEL
workninja-0.0.1.dist-info/top_level.txt
workninja-0.0.1.dist-info/RECORD
workninja-0.0.1.dist-info/METADATA
