Metadata-Version: 2.1
Name: workninja
Version: 0.0.1
Summary: Fast & Clever Work Manager Framework for Python
Home-page: https://github.com/fullzer4/WorkNinja
Author: fullzer4
Author-email: gabrielpelizzaro@gmail.com
License: UNKNOWN
Platform: UNKNOWN
Classifier: Programming Language :: Python :: 3
Classifier: License :: OSI Approved :: MIT License
Classifier: Operating System :: OS Independent
Requires-Python: >=3.6
